{
	"machine" : {
		"id" : "ciliamachine",
		"host" : "localhost",

		"connection" : 
			[
				{
				"out" : {
					"service_filter" : "(|(&(objectClass=fr.liglab.adele.cilia.remote.impl.AdminChainREST)(instance.name=remote-admin-chain-0))(&(objectClass=fr.liglab.adele.cilia.remote.impl.MonitorREST)(instance.name=remote-monitor-chain-0)))",
					"protocol" : ["jax-rs"], "exporter_filter" : "(instance.name=cilia.admin.exporter)"
					}, 
				"out" : {
					"service_filter" : "(cilia.exporter.protocol=jax-rs)",
					"protocol" : ["jax-rs"], "exporter_filter" : "(instance.name=cilia.jaxrs.exporter)"
					}, 
				"out" : {
					"service_filter" : "(cilia.exporter.protocol=ws)",
					"protocol" : ["ws"], "exporter_filter" : "(instance.name=cilia.ws.exporter)"
					}, 
				"out" : {
					"service_filter" : "(cilia.exporter.protocol=json-rpc)",
					"protocol" : ["json-rpc"], "exporter_filter" : "(instance.name=cilia.jsonrpc.exporter)"
					}, 
				"out" : {
					"service_filter" : "(cilia.exporter.protocol=xml-rpc)",
					"protocol" : ["xml-rpc"], "exporter_filter" : "(instance.name=cilia.xmlrpc.exporter)"
					}, 
				}
			],

		"component" : [
			{ 
			  "factory" : "RoSe_exporter.jersey",
			  "properties" : { "jersey.servlet.name" : "/cilia" , "instance.name":"cilia.admin.exporter"}
			}, 
			{ 
			  "factory" : "RoSe_exporter.jersey",
			  "properties" : { "jersey.servlet.name" : "/cilia/rest",  "instance.name":"cilia.jaxrs.exporter" }
			}, 
			{ 
			  "factory" : "RoSe_exporter.xmlrpc",
			  "properties" : { "xmlrpc.servlet.name" : "/cilia/xmlrpc",  "instance.name":"cilia.xmlrpc.exporter" }
			}, 
			{ 
			  "factory" : "RoSe_exporter.jsonrpc",
			  "properties" : { "jsonrpc.servlet.name" : "/cilia/jsonrpc", "instance.name":"cilia.jsonrpc.exporter" }
			}, 
			{ 
			  "factory" : "RoSe_exporter.cxf",
			  "properties" : { "cxf.servlet.name" : "/cilia/ws" , "instance.name":"cilia.ws.exporter" }
			}, 
		]
	}
}
